elementary_python_sdk/integrations/dqx/__init__.py
elementary_python_sdk/integrations/dqx/py.typed
elementary_python_sdk/integrations/dqx/runner.py
elementary_python_sdk_dqx-0.2.0.dist-info/METADATA
elementary_python_sdk_dqx-0.2.0.dist-info/WHEEL
elementary_python_sdk_dqx-0.2.0.dist-info/RECORD
