Metadata-Version: 2.4
Name: elementary-python-sdk-dqx
Version: 0.2.0
Summary: DQX integration for Elementary's Python SDK
Author: Elementary Data
Author-email: team@elementary-data.com
Requires-Python: >=3.10
Classifier: Programming Language :: Python :: 3
Classifier: Programming Language :: Python :: 3.10
Classifier: Programming Language :: Python :: 3.11
Classifier: Programming Language :: Python :: 3.12
Classifier: Programming Language :: Python :: 3.13
Classifier: Programming Language :: Python :: 3.14
Requires-Dist: databricks-cli (>=0.18.0)
Requires-Dist: databricks-connect (>=16.1.6)
Requires-Dist: elementary-python-sdk-core (==0.2.0)
Requires-Dist: pytz
